snaked/__init__.py
snaked_py-1.0.1.dist-info/LICENSE
snaked_py-1.0.1.dist-info/METADATA
snaked_py-1.0.1.dist-info/WHEEL
snaked_py-1.0.1.dist-info/top_level.txt
snaked_py-1.0.1.dist-info/RECORD
