Metadata-Version: 2.1
Name: snaked-py
Version: 1.0.1
Summary: Lightweight high-performance wrapper for accessing camelCase python objects using snake_case syntax.
Home-page: https://github.com/squirrel-preslash/snaked
Author: Squirrel-Preslash
License: MIT
Platform: UNKNOWN
Classifier: License :: OSI Approved :: MIT License
Classifier: Programming Language :: Python :: 3
Classifier: Programming Language :: Python :: 3.8
Requires-Dist: stringcase
